weixin/__init__.py
weixin/access_token_manager.py
weixin/api.py
weixin/callback.py
weixin/crypt.py
weixin/utils.py
weixins-0.1.0.dist-info/DESCRIPTION.rst
weixins-0.1.0.dist-info/METADATA
weixins-0.1.0.dist-info/RECORD
weixins-0.1.0.dist-info/WHEEL
weixins-0.1.0.dist-info/metadata.json
weixins-0.1.0.dist-info/top_level.txt
