Metadata-Version: 2.0
Name: weixins
Version: 0.1.0
Summary: A weixin api project
Home-page: https://github.com/ujsxn/weixin
Author: Nan Xiang
Author-email: 514580344@qq.com
License: GPLv3
Keywords: weixin wechat api
Platform: UNKNOWN
Classifier: Development Status :: 3 - Alpha
Classifier: Intended Audience :: Developers
Classifier: Topic :: Software Development
Classifier: License :: OSI Approved :: GNU General Public License v3 (GPLv3)
Classifier: Programming Language :: Python :: 2.7
Requires-Dist: redis
Requires-Dist: requests
